README.md
setup.py
wyfy/__init__.py
wyfy/wyfy.py
wyfy.egg-info/PKG-INFO
wyfy.egg-info/SOURCES.txt
wyfy.egg-info/dependency_links.txt
wyfy.egg-info/entry_points.txt
wyfy.egg-info/top_level.txt