Metadata-Version: 2.1
Name: wyfy
Version: 0.1
Summary: print wifi passwords (windows only)
Home-page: https://github.com/bnbdr/wyfy
Author: bnbdr
Author-email: bad.32@outlook.com
License: MIT
Keywords: wifi
Platform: UNKNOWN
Classifier: Intended Audience :: Developers
Classifier: Programming Language :: Python :: 2
Classifier: Programming Language :: Python :: 3
Classifier: License :: OSI Approved :: MIT License
